README.txt
setup.py
Products/__init__.py
Products.PloneboardPasteObject.egg-info/PKG-INFO
Products.PloneboardPasteObject.egg-info/SOURCES.txt
Products.PloneboardPasteObject.egg-info/dependency_links.txt
Products.PloneboardPasteObject.egg-info/entry_points.txt
Products.PloneboardPasteObject.egg-info/namespace_packages.txt
Products.PloneboardPasteObject.egg-info/not-zip-safe
Products.PloneboardPasteObject.egg-info/requires.txt
Products.PloneboardPasteObject.egg-info/top_level.txt
Products/PloneboardPasteObject/__init__.py
Products/PloneboardPasteObject/configure.zcml
Products/PloneboardPasteObject/browser/__init__.py
Products/PloneboardPasteObject/browser/configure.zcml
Products/PloneboardPasteObject/browser/context.py
Products/PloneboardPasteObject/browser/menu.py
docs/HISTORY.txt