Metadata-Version: 1.0
Name: Products.PloneboardPasteObject
Version: 1.0.0
Summary: fix for Ploneboard that allow you paste into some Ploneboard's archetypes
Home-page: UNKNOWN
Author: RedTurtle Technology
Author-email: sviluppoplone@redturlte.it
License: GPL
Platform: UNKNOWN
Classifier: Programming Language :: Python
Classifier: Topic :: Software Development :: Libraries :: Python Modules
